rutetider/__init__.py
rutetider/rutetider.py
rutetider/rutetider_utils.py
rutetider-1.0.2.dist-info/DESCRIPTION.rst
rutetider-1.0.2.dist-info/METADATA
rutetider-1.0.2.dist-info/RECORD
rutetider-1.0.2.dist-info/WHEEL
rutetider-1.0.2.dist-info/metadata.json
rutetider-1.0.2.dist-info/top_level.txt
