Metadata-Version: 2.0
Name: rutetider
Version: 1.0.2
Summary: Rutetider API wrapper
Home-page: https://github.com/DmytryiStriletskyi/rutetider
Author: DmytryiStriletskyi
Author-email: dmytryi.striletskyi@gmail.com
License: MIT
Download-URL: https://github.com/DmytryiStriletskyi/rutetider/archive/master.zip
Platform: UNKNOWN
Classifier: License :: OSI Approved :: MIT License
Classifier: Programming Language :: Python :: 2.7
Classifier: Programming Language :: Python :: 3.4
Classifier: Programming Language :: Python :: 3.5
Requires-Dist: psycopg2
